.gitattributes
.gitignore
CHANGELOG.md
LICENSE.txt
MANIFEST.in
README.md
didyoureadme.desktop
didyoureadme.pro
setup.py
didyoureadme/__init__.py
didyoureadme/didyoureadme.py
didyoureadme/libdbupdates.py
didyoureadme/libdidyoureadme.py
didyoureadme/shortcuts.py
didyoureadme/version.py
didyoureadme.egg-info/PKG-INFO
didyoureadme.egg-info/SOURCES.txt
didyoureadme.egg-info/dependency_links.txt
didyoureadme.egg-info/entry_points.txt
didyoureadme.egg-info/not-zip-safe
didyoureadme.egg-info/requires.txt
didyoureadme.egg-info/top_level.txt
didyoureadme/i18n/didyoureadme_es.qm
didyoureadme/i18n/didyoureadme_es.ts
didyoureadme/i18n/didyoureadme_fr.qm
didyoureadme/i18n/didyoureadme_fr.ts
didyoureadme/i18n/didyoureadme_ro.qm
didyoureadme/i18n/didyoureadme_ro.ts
didyoureadme/i18n/didyoureadme_ru.qm
didyoureadme/i18n/didyoureadme_ru.ts
didyoureadme/images/add.png
didyoureadme/images/admin.png
didyoureadme/images/alerta.png
didyoureadme/images/configure.png
didyoureadme/images/corona.png
didyoureadme/images/delete.png
didyoureadme/images/didyoureadme.ico
didyoureadme/images/didyoureadme.png
didyoureadme/images/didyoureadme.qrc
didyoureadme/images/didyoureadme_doxygen.png
didyoureadme/images/didyoureadme_rc.py
didyoureadme/images/document.png
didyoureadme/images/editar.png
didyoureadme/images/exit.png
didyoureadme/images/expired.png
didyoureadme/images/france.png
didyoureadme/images/group.png
didyoureadme/images/help.png
didyoureadme/images/kbabel.png
didyoureadme/images/keka.png
didyoureadme/images/keke.png
didyoureadme/images/keki.png
didyoureadme/images/keko.png
didyoureadme/images/mail.png
didyoureadme/images/open.png
didyoureadme/images/rumania.png
didyoureadme/images/rusia.png
didyoureadme/images/save.png
didyoureadme/images/search.png
didyoureadme/images/spain.png
didyoureadme/images/star.png
didyoureadme/images/statistics.png
didyoureadme/images/uk.png
didyoureadme/images/update.png
didyoureadme/images/user-add.png
didyoureadme/images/user.png
didyoureadme/ui/Ui_frmAbout.py
didyoureadme/ui/Ui_frmAccess.py
didyoureadme/ui/Ui_frmDocumentsIBM.py
didyoureadme/ui/Ui_frmGroupsIBM.py
didyoureadme/ui/Ui_frmHelp.py
didyoureadme/ui/Ui_frmMain.py
didyoureadme/ui/Ui_frmSettings.py
didyoureadme/ui/Ui_frmUsersIBM.py
