Metadata-Version: 2.1
Name: didyoureadme
Version: 20181122
Summary: System to control who and when a group reads a document send by mail. It uses postgresql to store information
Home-page: https://github.com/Turulomio/didyoureadme
Author: Turulomio
Author-email: turulomio@yahoo.es
License: GPL-3
Keywords: mail read when who
Platform: UNKNOWN
Classifier: Development Status :: 5 - Production/Stable
Classifier: Intended Audience :: End Users/Desktop
Classifier: License :: OSI Approved :: GNU General Public License v3 (GPLv3)
Classifier: Programming Language :: Python :: 3
